pyarks/__init__.py
pyarks/park.py
pyarks/ride.py
pyarks/utility.py
pyarks/universal/IslandsOfAdventure.py
pyarks/universal/UniversalStudiosFlorida.py
pyarks/universal/UniversalStudiosHollywood.py
pyarks/universal/UniversalStudiosJapan.py
pyarks/universal/VolcanoBay.py
pyarks/universal/__init__.py
pyarks/universal/universalUS.py
pyarks-0.1.4.dist-info/METADATA
pyarks-0.1.4.dist-info/RECORD
pyarks-0.1.4.dist-info/WHEEL
pyarks-0.1.4.dist-info/top_level.txt
