Metadata-Version: 2.1
Name: pyarks
Version: 0.1.4
Summary: A package to get wait times from amusement parks
Home-page: http://github.com/joshimbriani/Pyarks
Author: Josh Imbriani
Author-email: pypi@joshimbriani.com
License: MIT
Download-URL: https://github.com/joshimbriani/Pyarks/archive/v0.1.4.tar.gz
Platform: UNKNOWN
Requires-Dist: requests (>=2.21.0)
Requires-Dist: arrow (>=0.11.0)
